{"title":"TS 01 Otitis media aguda pediatría","guid":"","filepath":"/Users/criaah/Vault/📚 Resources/Mapas-Mentales/Entidades clínicas/Pediatría/Ped TS 01 Otitis media aguda pediatría.smmx","root":{"id":"0","parent":"-1","text":"Otitis media aguda\\NOMA","guid":"AJ8JTjRXrNiIg3I1CDiNaQ","children":[{"id":"1","parent":"0","text":"Definición ","guid":"rxdAJxwPafzlTFYQT7h7rg","children":[{"id":"2","parent":"1","text":"Abombamiento membrana timpánica\\No\\NOtorrea de nueva aparición sin OEA","guid":"bSKcZXrhNJJQy9y0tNLY5Q","children":[]},{"id":"3","parent":"1","text":"Signos infecciosos agudos","guid":"8C0-iitMKzt-vzsTBvIyfg","children":[]},{"id":"4","parent":"1","text":"Signos de otitis media","guid":"","children":[]}]},{"id":"5","parent":"0","text":"Epidemiologia","guid":"SLB2L2iT226r39OEM202rw","children":[{"id":"6","parent":"5","text":"Incidencia","guid":"ssFj8r8GQUmHRRol9dpQIQ","children":[{"id":"7","parent":"6","text":"60-80% >1 al 1ā","guid":"tDX_oG3IHxH34mkCQBWtxQ","children":[]},{"id":"8","parent":"6","text":"80-90% a los 2-3ā","guid":"ZjJDPgBaULzFhd1nloc8DA","children":[]}]},{"id":"9","parent":"5","text":"Factores de riesgo","guid":"yUNyFLgq4mI21HjMYg6yFg","children":[{"id":"10","parent":"9","text":"Edad","guid":"X8tWX2Arhj4QYrvAMpLaAg","children":[{"id":"11","parent":"10","text":"6-18 meses de edad","guid":"e_9_KbmhBGnJ3vJCZB98Ng","children":[]},{"id":"12","parent":"10","text":"5-6 ā","guid":"9t1qYdftok77M__FoqgRjQ","children":[]}]},{"id":"13","parent":"9","text":"Humo cigarro o contaminación","guid":"UQsrWEWZU7mok2xuXlQBaA","children":[]},{"id":"14","parent":"9","text":"Estación fria","guid":"skjdpDg5NseEsamiLdUvKA","children":[{"id":"15","parent":"14","text":"Otoño-Invierno ","guid":"M2mkRUH1SqgLnLSqgIvP2g","children":[]}]},{"id":"16","parent":"9","text":"Guardería/Jardín infantil","guid":"2x9ykKPQmGQWcd8CyAF86g","children":[]},{"id":"17","parent":"9","text":"Enfermedad respiratoria alta asociada","guid":"2HeLNvX5n0FWnSw3RXx4nw","children":[]},{"id":"18","parent":"9","text":"Antecedentes familiares","guid":"RymK_Rt6alUhEYHc4_CqBA","children":[]},{"id":"19","parent":"9","text":"Lactancia materna","guid":"V2zfAG89YZjNiePBCpH8wQ","children":[]},{"id":"20","parent":"9","text":"Chupete","guid":"jqjYI6Qy43s-OSHxUJBVsA","children":[]},{"id":"21","parent":"9","text":"Raza/etnia","guid":"IrHK9G4SelfOvRZfcVMDAw","children":[]},{"id":"22","parent":"9","text":"Países en desarrollo","guid":"_c7ct1EwEvYNUYRJ5cfRdw","children":[]},{"id":"23","parent":"9","text":"Condiciones socio-economías","guid":"uSVYrCPD7xIGl7-4aChb-A","children":[{"id":"24","parent":"23","text":"Hacinamiento","guid":"MnOL2P_WLsu_Ax6ezwUM8g","children":[]}]},{"id":"25","parent":"9","text":"Alteración inmune","guid":"BVvtSJL-TOLYc05rjeh76Q","children":[{"id":"26","parent":"25","text":"Sd Down","guid":"P2tysutZmR71BiPhcT73Qg","children":[]},{"id":"27","parent":"25","text":"Paladar hendido","guid":"J28KwUQIvqQ6o7ihf8tfuA","children":[]},{"id":"28","parent":"25","text":"Rinitis alérgica","guid":"m1cK2zpBKt8Yrmhv9ywsfw","children":[]}]}]}]},{"id":"29","parent":"0","text":"Patogenesis ","guid":"WnAlQMW_Inp8xclx6LxYDA","children":[{"id":"30","parent":"29","text":"Anatomía oído medio","guid":"c24bUl5kNlzxPYF1T31kvQ","children":[{"id":"31","parent":"30","text":"Orificios ","guid":"anIAewJDZK5b1BTaXP3iPg","children":[{"id":"32","parent":"31","text":"Orificios nasales","guid":"6XM4cpdwLkE0LNv_XFdXOg","children":[]},{"id":"33","parent":"31","text":"Trompa de Eustaquio","guid":"HhDPHJ71aDus9uwD6PdTMA","children":[]},{"id":"34","parent":"31","text":"Celdas mastoideas ","guid":"Peq1Hqvi-hlEBxBPBtVl3Q","children":[]}]}]},{"id":"35","parent":"29","text":"Extensión\\NComplicaciones","guid":"s6EJuoHJhueOTuX3Ia66Sg","children":[{"id":"36","parent":"35","text":"Mastoidits ","guid":"Z974plB63JOj6I7sInV8Pw","children":[]},{"id":"37","parent":"35","text":"Laberintitis ","guid":"VGFd97Se-xn72h1qptBeCg","children":[]},{"id":"38","parent":"35","text":"Petrositis ","guid":"-rO39zns91LMrTSenpSSVQ","children":[]},{"id":"39","parent":"35","text":"Meningitis","guid":"eASpZgF6NbU3cWbmlxN9yA","children":[]},{"id":"40","parent":"35","text":"Trombosis del\\Nseno lateral","guid":"rXkqw4x4se-_SW7YtzYDGA","children":[]}]},{"id":"41","parent":"29","text":"Infección tracto\\Nrespiratorio alto","guid":"LyMeQpJxSggF9eSpSxLEQQ","children":[]},{"id":"42","parent":"29","text":"Inflamación mucosa nariz,\\Nnasofaringe y trompa de Eustaquio","guid":"20o_6hiTzNCddbfTsxImjw","children":[]},{"id":"43","parent":"29","text":"Estrechamiento itsmo\\Ntrompa Eustaquio","guid":"W26ugJCnMM18t79lNzeakg","children":[{"id":"44","parent":"43","text":"Mala ventilación ","guid":"ezTi92LMlmNhfeGQeE7FQA","children":[]},{"id":"45","parent":"43","text":"Presión negativa\\Noído medio","guid":"Op-ThTipwi-NtIm4IjViGg","children":[]}]},{"id":"46","parent":"29","text":"Acumulación\\Nsecreciones oído medio","guid":"SHzcBBADJz-38dpriCxWYg","children":[]},{"id":"47","parent":"29","text":"Bacterias que colonizan vía\\Naérea entran a oído medio","guid":"TpNI6FdgdvEbcqWR6BsdRQ","children":[{"id":"48","parent":"47","text":"Aspiración","guid":"nXS11D27RK-ChGuENRm4wg","children":[]},{"id":"49","parent":"47","text":"Reflujo","guid":"9X0K64FdJmz_b9gqusQ2lA","children":[]},{"id":"50","parent":"47","text":"Insuflación","guid":"UMshUtByW2lNsqcF4oTGqA","children":[]}]},{"id":"51","parent":"29","text":"Crecimiento\\Nbacteriano y clínica","guid":"S5tmDvJ0iy6SLWnofE6qEg","children":[]},{"id":"52","parent":"29","text":"Efusión se puede mantener por semanas\\No meses de resuelta la infección","guid":"skB__mbxuKWVol4fV4oV9Q","children":[]}]},{"id":"53","parent":"0","text":"Microbiología ","guid":"2I3EdYGHCcId5EbyT8oOgQ","children":[{"id":"54","parent":"53","text":"Generalidades","guid":"W0VqczV9_5xCoiOHJ5iHYQ","children":[{"id":"55","parent":"54","text":"90% Bacteriana","guid":"CHNlEhjBUdhBFTuL6bqxyA","children":[]},{"id":"56","parent":"54","text":"70% Viral","guid":"Bsjcwl7Mx5IPSat0-pQnHw","children":[]},{"id":"57","parent":"54","text":"60% Mixtas","guid":"Ovlr09-Yq6SiNQI9d3FZxg","children":[{"id":"58","parent":"57","text":"Menos penetrancia\\Nantibióticos","guid":"fa1f8HIfELiWkEkC_zxx8Q","children":[]}]}]},{"id":"59","parent":"53","text":"Bacteriana","guid":"8KxTl1pUMw7BaJWsp620rQ","children":[{"id":"60","parent":"59","text":"Streptococcus\\Npneumoniae","guid":"qBm6to7wx8ChQSqAH-WRdw","children":[{"id":"61","parent":"60","text":"General","guid":"","children":[{"id":"62","parent":"61","text":"Vacuna neumococica 7 conjugada\\N< Prevalencia","guid":"KagkCUrnzBnKo33D8NkeBw","children":[]},{"id":"63","parent":"61","text":"Bilateral o unilateral","guid":"yTv_rTgoJ-1uggz1wsE_VQ","children":[]}]},{"id":"64","parent":"60","text":"50% de los casos","guid":"iQ_AnSafXCSg-hH9G4elgg","children":[{"id":"65","parent":"64","text":"Severa","guid":"J43h9am1qmaq3yrJ2ww_1Q","children":[]},{"id":"66","parent":"64","text":"Persistente","guid":"ZF22ulFh8BQxqpHvOa7hcQ","children":[{"id":"67","parent":"66","text":"Resistencia?","guid":"","children":[]}]},{"id":"68","parent":"64","text":"Refractaria","guid":"Cg2hWjzXNt_3X8gdSVgLFQ","children":[]}]},{"id":"69","parent":"60","text":"Generalmente\\Nprimer episodio","guid":"FV5wrDryisovbHKnJMYHmQ","children":[]},{"id":"70","parent":"60","text":"Clínica","guid":"o6JXS6VJYSZeRSqozcImIA","children":[{"id":"71","parent":"70","text":"Fiebre alta","guid":"DH7z_peQz2IJKWEv-rReKw","children":[]},{"id":"72","parent":"70","text":"Intensa Otalgia","guid":"XjAaxYvVPH4iJ7NbDAuk2A","children":[]},{"id":"73","parent":"70","text":"Complicaciones","guid":"YdCGgGvEqAfzl3Cc37mg0A","children":[{"id":"74","parent":"73","text":"Mastoiditis ","guid":"y4ODYm2aExFW1n-aZJWs6A","children":[]},{"id":"75","parent":"73","text":"Bacteremia","guid":"jZ4NPcGUWHTXwBjLlJHz4A","children":[]}]}]}]},{"id":"76","parent":"59","text":"Haemophilus\\Ninfluenzae","guid":"jDJ6lKRekFvmS1KYwiRPBA","children":[{"id":"77","parent":"76","text":"Bilateral","guid":"6QyjtUdiMdyWaZv-_TpMeA","children":[]},{"id":"78","parent":"76","text":"45% de los casos","guid":"5RJItniNDPjents9TUbxOw","children":[{"id":"79","parent":"78","text":"Severa","guid":"IVdADYaB886n8JiDIxGw7g","children":[]},{"id":"80","parent":"78","text":"Persistente","guid":"F3HulLSDrvCuvx-KnzLx2A","children":[]},{"id":"81","parent":"78","text":"Refractaria","guid":"6Lk0zggug6HwoZmWMav63g","children":[]}]},{"id":"82","parent":"76","text":"Clínica","guid":"yjFNImwY0u-I0hbfP02uiQ","children":[{"id":"83","parent":"82","text":"Conjuntivitis\\Ninterrecurrente","guid":"","children":[]},{"id":"84","parent":"82","text":"Menos síntomas","guid":"vmMW9vixKoGKY-rM9AbGLA","children":[{"id":"85","parent":"84","text":"Fiebre baja","guid":"NJy6j6EKHltVR4CDlp8hBw","children":[]},{"id":"86","parent":"84","text":"Membrana timpánica\\Nmenos inflamada","guid":"2kTlD8g8joIMoVHmkk4VQg","children":[]}]}]},{"id":"87","parent":"76","text":"Mayores\\Ncomplicaciones","guid":"ybFsYBycyeTKpRLxbipJTA","children":[{"id":"88","parent":"87","text":">Fracaso tratamiento adecuado","guid":"iFHEMDrlOl9YtJiuv1-UIg","children":[]},{"id":"89","parent":"87","text":"Cronicidad","guid":"","children":[]},{"id":"90","parent":"87","text":"1/3 a 1/4 producen betalactamasas","guid":"OIHJMd5QXY71d0EQJE6VJg","children":[]}]}]},{"id":"91","parent":"59","text":"Moraxella catarrhalis ","guid":"jPw3YaXufQfVyqt1lEHN7g","children":[{"id":"92","parent":"91","text":"10% casos","guid":"Gc3l0CUFtnUijO95iOZehw","children":[]},{"id":"93","parent":"91","text":"90% produce\\Nbetalactamasas","guid":"nzeWiDk4Ty9Viqc-F_VQ4w","children":[]}]},{"id":"94","parent":"59","text":"Streptococcus grupo A","guid":"XpqqDon1tyXtabl7reiIAQ","children":[{"id":"95","parent":"94","text":"5-10% casos","guid":"-MnEGZoMcZYRs_XHTLK4qg","children":[]},{"id":"96","parent":"94","text":"Niños mayores","guid":"-JWGcSfwYPn7BTkWQJRbyA","children":[]},{"id":"97","parent":"94","text":"Mayores\\Ncomplicaciones","guid":"lz2zZgictvdonKFWech7_A","children":[{"id":"98","parent":"97","text":"Perforación membrana timpánica","guid":"ll2-YJIOmBn4eOFoiNJOCw","children":[]},{"id":"99","parent":"97","text":"Mastoiditis ","guid":"","children":[]}]},{"id":"100","parent":"94","text":"Clínica","guid":"vzEXSUk0Yz3RXcu_NV6oOg","children":[{"id":"101","parent":"100","text":"< Síntomas sistemicos ","guid":"77qGKVNadZMrRCH1BnxhHA","children":[]}]}]},{"id":"102","parent":"59","text":"Staphilococcus aureus","guid":"durIL7wQ5lnh0P2w-XfJ8A","children":[{"id":"103","parent":"102","text":"Poco frecuente ","guid":"xbNi0Se2-OQzk7sMYfKoJQ","children":[{"id":"104","parent":"103","text":"En aumento","guid":"","children":[]}]},{"id":"105","parent":"102","text":"Otorrea en tubos de ventilación","guid":"lbit3Vi3HZzod7q6_bJeaA","children":[]}]},{"id":"106","parent":"59","text":"Otras bacterias","guid":"h7Z3ZhscZgF3A4s8X4m2oQ","children":[{"id":"107","parent":"106","text":"E. Coli ","guid":"ySMiYt_l21arDV3NJM8pdA","children":[{"id":"108","parent":"107","text":"RN","guid":"","children":[]}]},{"id":"109","parent":"106","text":"Pseudomona\\Naeruginosa ","guid":"t9ye1q-55obWYeDieoEaJw","children":[{"id":"110","parent":"109","text":"OMC supurativa ","guid":"Q82Qf7mbxQxkQUWLspr1Nw","children":[]}]}]}]}]},{"id":"111","parent":"0","text":"Clínica","guid":"OzVvsi1_LWOYNhudmPjJKg","children":[{"id":"112","parent":"111","text":"General","guid":"TMdHZL9we6qWAk1PzTiyNw","children":[{"id":"113","parent":"112","text":"Inespecificos ","guid":"BG7sEjWeYIXYrdn465CJvw","children":[{"id":"114","parent":"113","text":"Fiebre","guid":"efHWAG72k2ENmfYgV5y0Dw","children":[]},{"id":"115","parent":"113","text":"Irritabilidad","guid":"0mBuRS726Lkj5xvpsH84uQ","children":[]},{"id":"116","parent":"113","text":"Cefalea","guid":"872393eaR8aGeAcMLgy_og","children":[]},{"id":"117","parent":"113","text":"Apatía","guid":"pANDHGre1rPRHL_-o_g-qw","children":[]},{"id":"118","parent":"113","text":"Anorexia","guid":"xxlBNhZGdjrd_leE_TeACg","children":[]},{"id":"119","parent":"113","text":"Vomitos","guid":"0BY2Fd2dnuPo6hLFfLZ34Q","children":[]},{"id":"120","parent":"113","text":"Fiebre","guid":"_gj0Dln-hyNk8auU8I0p7w","children":[{"id":"121","parent":"120","text":"Si >40C","guid":"dFtlF4yTI-K0z6QyTIDH1Q","children":[{"id":"122","parent":"121","text":"Bacteremia?","guid":"UGH_kkStZfCs6es-7Ef4Tg","children":[]},{"id":"123","parent":"121","text":"Otro foco?","guid":"3YaZpI3SfBD5Sj70XOq4aw","children":[]}]}]}]},{"id":"124","parent":"112","text":"Otalgia","guid":"IumRXr9OfQxiw2GPmO7eRQ","children":[{"id":"125","parent":"124","text":"Principal síntoma","guid":"MjbxIllBzH75nGXFOOunKQ","children":[]},{"id":"126","parent":"124","text":"Mejor predictor ","guid":"UrZrhO62H6cNTV5V1hdRdQ","children":[]},{"id":"127","parent":"124","text":"No siempre presente","guid":"NWdAaZiWzfzneq0IvwUP_w","children":[]}]},{"id":"128","parent":"112","text":"Pérdida de audición","guid":"0hmZzXmJgti55fTIssp6Mg","children":[]},{"id":"129","parent":"112","text":"Otorrea","guid":"8W1BJolcoWBwFpi9CPfdew","children":[]},{"id":"130","parent":"112","text":"Efusión de la membrana timpánica","guid":"dpLCoLFyifTPEubUIykQcA","children":[]},{"id":"131","parent":"112","text":"Asociados a\\Ncomplicaciones","guid":"ThzyOzrRO3ZQ-4L-SfNWuw","children":[{"id":"132","parent":"131","text":"Zumbido de oídos","guid":"KkMnAfu4a6ui07V4sg-LdQ","children":[]},{"id":"133","parent":"131","text":"Vértigo","guid":"O6CaLgJxNFSbsQzDRZxDhw","children":[]},{"id":"134","parent":"131","text":"Nistagmus","guid":"qBCXArM9ZBhGDSto39YA3w","children":[]},{"id":"135","parent":"131","text":"Hinchazón de oreja","guid":"Wu_8Tn9Xxi8AZO4FdEFRYw","children":[]},{"id":"136","parent":"131","text":"Parálisis facial","guid":"VcAaRw0UEst30lrhcfK3qA","children":[]}]}]},{"id":"137","parent":"111","text":"Síndromes clínicos","guid":"7MQWSeTwAwk2UUbi417qPw","children":[{"id":"138","parent":"137","text":"Otitis conjuntivitis","guid":"SXzZL3hZ3WWK5UgyCDuyuQ","children":[{"id":"139","parent":"138","text":"Otitis media","guid":"EJ3FVn9LffDGB9XxKTuZTA","children":[]},{"id":"140","parent":"138","text":"Conjuntivitis pustulosa","guid":"","children":[]}]},{"id":"141","parent":"137","text":"Miringitis bulosa\\NTimpanitis ampollar","guid":"HVq-qs3wnLFtphHNMVqliA","children":[{"id":"142","parent":"141","text":"Ampollas en membrana timpánica","guid":"QP2WgI7oxNUtkjgMqiiKTw","children":[]},{"id":"143","parent":"141","text":"DD Sd Ramsay Hunt","guid":"T97IyOtuB2IRwT6BwC0Eng","children":[]}]}]}]},{"id":"144","parent":"0","text":"Diagnóstico","guid":"srVs8iQKHJzNlDJCWBoMcw","children":[{"id":"145","parent":"144","text":"Procedimientos","guid":"P5x0MRYxd4sXDuLrsSQOZg","children":[{"id":"146","parent":"145","text":"Otoscopia","guid":"S0CnlxcfntPOnG4NjS99WQ","children":[{"id":"147","parent":"146","text":"Color","guid":"gJ7gBK6HjR5aBZL7dg1g7A","children":[{"id":"148","parent":"147","text":"Gris nacarado","guid":"jvMoABh_x3XLQGl06VWAFg","children":[{"id":"149","parent":"148","text":"Normal","guid":"","children":[]}]},{"id":"150","parent":"147","text":"Rosa","guid":"W6MtV2MmRNr-C3RgcCdNwQ","children":[]},{"id":"151","parent":"147","text":"Blanco tiza","guid":"juQg2EjmHReSQphb1n2nEg","children":[{"id":"152","parent":"151","text":"Timpanoesclerosis\\NMiringoesclerosis","guid":"TROcKqS4F5ObRDd02KJgiA","children":[]}]},{"id":"153","parent":"147","text":"Rojo","guid":"VQugeTlnWR9Zfr6in9u89Q","children":[{"id":"154","parent":"153","text":"Inflamación","guid":"1C76pQ6mrOCgz6MW2468Ow","children":[]},{"id":"155","parent":"153","text":"Hiperhemia","guid":"QmUQumxAsHCgQTbDtDgfrw","children":[{"id":"156","parent":"155","text":"Manipulación","guid":"6TQBMHSNtBEVLWp8Cy7dnw","children":[]}]}]},{"id":"157","parent":"147","text":"Gris","guid":"4WaFgNbRnS2S4kf7_-2fzQ","children":[]},{"id":"158","parent":"147","text":"Blanco","guid":"fi0djP_xc47p0bJnBFz23w","children":[{"id":"159","parent":"158","text":"Líquido ceroso\\NOME","guid":"","children":[]}]},{"id":"160","parent":"147","text":"Azul","guid":"N1ODT6kU3eNifIgeAWPgOg","children":[]},{"id":"161","parent":"147","text":"Blanco","guid":"SKr1AM3crE2j0e0tIRIQjw","children":[{"id":"162","parent":"161","text":"Líquido purulento\\NOMA","guid":"yXRGOchke24fT2W43EHGiw","children":[]}]},{"id":"163","parent":"147","text":"Amarillo pálido","guid":"wN8Df_ixXAzvkI9LgVU3Og","children":[]}]},{"id":"164","parent":"146","text":"Posición","guid":"5wxk-B8lxBZ14XLltL_JiA","children":[{"id":"165","parent":"164","text":"Neutral","guid":"jKQ9AJs2tNQh9Hse-DM8SA","children":[{"id":"166","parent":"165","text":"Normal","guid":"wD_qHRtDXUi-CbUURmTEOw","children":[]}]},{"id":"167","parent":"164","text":"Retraída","guid":"pEInEl28kzrSu0H87EtMkA","children":[{"id":"168","parent":"167","text":"Presión negativa","guid":"Q0LghbjGs0OlddtOvKeOWg","children":[{"id":"169","parent":"168","text":"Otitis media persistente","guid":"efQcIZhzJ4YXTeEWf0mpcA","children":[]}]}]},{"id":"170","parent":"164","text":"Completa","guid":"mNkCsYJxT00ZCn8Stwn3ug","children":[{"id":"171","parent":"170","text":"Presión positiva","guid":"89wftF7ftQHIgGmJaZAKXw","children":[{"id":"172","parent":"171","text":"Otitis media aguda","guid":"","children":[]}]}]},{"id":"173","parent":"164","text":"Abultamiento ","guid":"j0iJbciNN86mHYHRMWCkzA","children":[]}]},{"id":"174","parent":"146","text":"Superficie","guid":"PdBEyXKymQhIikhVm-etvQ","children":[{"id":"175","parent":"174","text":"Nivel del líquido ","guid":"QNf0xJ7hR3JXkCYcqCYjBw","children":[]},{"id":"176","parent":"174","text":"Burbujas","guid":"yxcC4LQCtnD2rR3wCH_SfA","children":[]},{"id":"177","parent":"174","text":"Perforación","guid":"6sExpKwcYWLC5c0FhGMSPw","children":[]},{"id":"178","parent":"174","text":"Otorrea","guid":"5YkHQ5R80izSuwdaOW5Eig","children":[]},{"id":"179","parent":"174","text":"Bulas","guid":"3PFPRZwD1q1GAwc6sl7KbA","children":[]},{"id":"180","parent":"174","text":"Timpanoesclerosis \\NCicatrices","guid":"xhYwDFw6Y3T9m5oz_sKZew","children":[]},{"id":"181","parent":"174","text":"Zonas de atrofia","guid":"FbSLxWXspcJXSDk8QcJT_w","children":[]},{"id":"182","parent":"174","text":"Bolsas de retracción","guid":"-RWB9YQP57cjjDWBp141qA","children":[]},{"id":"183","parent":"174","text":"Colesteatoma ","guid":"BZfteUn1PSBrm0ZlxrQJuA","children":[]},{"id":"184","parent":"174","text":"Cono luminoso","guid":"6kmtiqsSIunCKwB5pe25YQ","children":[{"id":"185","parent":"184","text":"Sin importancia clínica","guid":"se0OmdoZLQkeoQGqR1sQGA","children":[]},{"id":"186","parent":"184","text":"Desaparece en otitis?","guid":"","children":[]}]},{"id":"187","parent":"174","text":"Movilidad","guid":"9_4QNCYKJ1ACVYpuYDtZTw","children":[{"id":"188","parent":"187","text":"Otoscopia neumatica","guid":"","children":[]},{"id":"189","parent":"187","text":"Asegurar que no existan fugas","guid":"GavyHBIBY5pIS-iIIrln6g","children":[]}]},{"id":"190","parent":"174","text":"Translucidez","guid":"28sihHOd3K9po0nkWeVHNA","children":[{"id":"191","parent":"190","text":"Normalmente translúcida","guid":"pc93gUvCzgteVd1D93QqDA","children":[]},{"id":"192","parent":"190","text":"Presencia de niveles hidro-aéreos","guid":"FTgTcbdmcAeODUwOIDsacg","children":[{"id":"193","parent":"192","text":"EOM/OMA","guid":"OdUpyGuYSi15yj-A_IrX3g","children":[]}]}]}]},{"id":"194","parent":"146","text":"Conducto auditivo externo\\Ny pabellón auricular","guid":"fwTayPpsIFzVyVu2r00G5w","children":[{"id":"195","parent":"194","text":"Deformaicon","guid":"SgDn2oMCTbX4MT66bi_OgA","children":[]},{"id":"196","parent":"194","text":"Desplazado","guid":"5VWZHvlksLGk56_VLi-Orw","children":[]},{"id":"197","parent":"194","text":"Inflamado","guid":"sB0CzpR5MgyVslpD09_6AA","children":[]},{"id":"198","parent":"194","text":"Cuerpo extraño","guid":"q4Srtvmk1Vf3dYJE49wyjw","children":[]}]}]},{"id":"199","parent":"145","text":"Tímpanometria y\\Nreflectometria acústica","guid":"ihHckJmrDxDO8BowASeLQw","children":[{"id":"200","parent":"199","text":"Efusión ","guid":"","children":[]}]}]},{"id":"201","parent":"144","text":"OMA","guid":"Cv6PiBv_iiEldvy7_97-XQ","children":[{"id":"202","parent":"201","text":"Efusión del oído medio","guid":"rPoU9M89Ajay4yONWORz4g","children":[{"id":"203","parent":"202","text":"Otorrea","guid":"zKxIMUqBSgfHT8T67Lh4dw","children":[{"id":"204","parent":"203","text":"Que no se debe a otitis externa","guid":"98Yw-AUIZAf4VGZTytV7yg","children":[]}]},{"id":"205","parent":"202","text":"Criterios diagnósticos\\NEOM","guid":"a48mFEsto9JzXOqQRJn4HQ","children":[{"id":"206","parent":"205","text":"Nivel aire líquido o burbujas","guid":"Hg0tZZt2EOyhqdHXV90ijQ","children":[]},{"id":"207","parent":"205","text":"Dos o más","guid":"L8xTUETSQ64u8m0qzTowEA","children":[{"id":"208","parent":"207","text":"Variación de color","guid":"O73Tk83fDWIe-dIRhjyHPA","children":[]},{"id":"209","parent":"207","text":"Opacidad","guid":"c1tpaG0KkLIZmjbKh5nYmA","children":[]},{"id":"210","parent":"207","text":"Deterioro de movilidad","guid":"","children":[]}]}]}]},{"id":"211","parent":"201","text":"Signos y síntomas de\\Ninflamación del oído medio","guid":"WYTzAzbO_Xe87IJ8Ru0uIg","children":[{"id":"212","parent":"211","text":"Abultamiento membrana timpánica","guid":"OkYRXl_QI_PYwzk7Kk6PAg","children":[]},{"id":"213","parent":"211","text":"Eritema membrana timpánica","guid":"Dx4tboYtqb_xN6GYVnoc-w","children":[]},{"id":"214","parent":"211","text":"Otalgia","guid":"RDrzxLcg8Rue55Sn41y4DQ","children":[]},{"id":"215","parent":"211","text":"Fiebre","guid":"zR51eRBb7WKESjjWMgwyhA","children":[]}]}]},{"id":"216","parent":"144","text":"Etiología\\NPistas","guid":"NuYH7qAPSRhluDT9Qie1Vg","children":[{"id":"217","parent":"216","text":"Haemophillus\\Ninfluenzae","guid":"aa7FRF9sG5uWLn-x3FTs2Q","children":[{"id":"218","parent":"217","text":"Conjuntivitis","guid":"Bbgt4HeJz-dSank_VWTjXA","children":[]},{"id":"219","parent":"217","text":"Bilateral ","guid":"TwHI0P5IVIAP7a_I6BrlAg","children":[]}]},{"id":"220","parent":"216","text":"S. Pneumoniae","guid":"JdcGw42mxCxztydAY5XSdw","children":[{"id":"221","parent":"220","text":"Uni-bilateral ","guid":"oUSqPSs6zGmQ2h-mC_q0dQ","children":[]},{"id":"222","parent":"220","text":"Muy sintomática","guid":"65AE6oF5se7rHGZkq6xZYA","children":[]}]},{"id":"223","parent":"216","text":"Perforación timpánica","guid":"I9HrnQL48GxlQfP0UxTZTg","children":[{"id":"224","parent":"223","text":"Más frecuente en\\NS. Pyogenes","guid":"eO5_yI3bl-NfJ0ct5-OiGg","children":[]}]}]}]},{"id":"225","parent":"0","text":"Complicaciones\\Ny secuelas","guid":"imrL6e3oEBJHWMGaNITemg","children":[{"id":"226","parent":"225","text":"Intratratemporales\\Nexteacraneales","guid":"OiDpilTje1-sSCWm9voeZg","children":[{"id":"227","parent":"226","text":"Hipoacusia conductiva\\Npersistente y fluctuante","guid":"tuRlF4gJLGjww3KUN2MkpQ","children":[{"id":"228","parent":"227","text":"Persiste meses\\No semanas","guid":"wyQV8wFmwMhX3mqIKvgVXA","children":[]},{"id":"229","parent":"227","text":"Pérdida neurosensorial\\Npoco frecuente","guid":"uF9wmAfyNsAteUtTRAjxfQ","children":[]}]},{"id":"230","parent":"226","text":"Problema\\Nequilibrio-motor","guid":"equ_B1DugQ1f9PGVOnADSA","children":[{"id":"231","parent":"230","text":"Disfunción laberíntica","guid":"Bp51HZuozXuV94fo425Lzg","children":[]},{"id":"232","parent":"230","text":"Laberintitis ","guid":"t-wh-EWTyt6HWH33D1A4xw","children":[]}]},{"id":"233","parent":"226","text":"Membrana timpánica","guid":"VAiL5OAAJE-gA3TyXWxZew","children":[{"id":"234","parent":"233","text":"Timpanoesclerosis","guid":"S2Ml6k_wUIneYb5GnlkmGQ","children":[]},{"id":"235","parent":"233","text":"Perforación","guid":"02yWUNqaDneF6Tfer_M4Wg","children":[]},{"id":"236","parent":"233","text":"Otitis media supurativa crónica o\\Notomastoiditis crónica","guid":"-e8PpaKz2T1NTopvyiRD9Q","children":[{"id":"237","parent":"236","text":"Perforación con drenaje\\Npurulento más de 6 semanas","guid":"bazMuWAaIe3upxxxym3vKg","children":[]}]}]},{"id":"238","parent":"226","text":"Colesteatoma ","guid":"6InXjoSgsx4mCbW8oDa9JQ","children":[{"id":"239","parent":"238","text":"Crecimiento anormal","guid":"3LIOdFLzjpNSIEUo4cOnVA","children":[{"id":"240","parent":"239","text":"Epitelio escamoso ","guid":"LM5pVbLgCmsJX3tXeR8sAg","children":[]},{"id":"241","parent":"239","text":"Mastoides","guid":"Y0kRNXu94Owz-wN1Fk36wA","children":[]}]},{"id":"242","parent":"238","text":"Puede destruir huesecillos","guid":"1NmQxVYihZjRZnvOz7hubg","children":[]},{"id":"243","parent":"238","text":"FR\\NOtitis media recurrente","guid":"2OjcoAb7e7tdoGs2k0bFAg","children":[]}]},{"id":"244","parent":"226","text":"Mastoiditis ","guid":"KOZz3XYtIsu42C2-sPhxug","children":[]},{"id":"245","parent":"226","text":"Parálisis facial","guid":"pyix5EIkekvIYHGk22kC5A","children":[]},{"id":"246","parent":"226","text":"Petrositis ","guid":"D3beVdndzW39Sogns7cjfA","children":[]}]},{"id":"247","parent":"225","text":"Complicaciones\\Nintracraneales","guid":"xAx687VU5CAhF5CvuYkAug","children":[{"id":"248","parent":"247","text":"Meningitis","guid":"dQ5vr4OlP6GaltLBUaSPAg","children":[]},{"id":"249","parent":"247","text":"Absceso cerebral ","guid":"o3EKR5UkgBTzPb4tSAZhfg","children":[]},{"id":"250","parent":"247","text":"Absceso epidural ","guid":"L4Ute83qY3ll5rOpuVb6XQ","children":[]},{"id":"251","parent":"247","text":"Trombosis seno lateral","guid":"uteLf8YQMy84q5ZO1gk11w","children":[]},{"id":"252","parent":"247","text":"Trombosis seno cavernoso","guid":"OZ-lYT5un2HkN_sU5_cPxw","children":[]},{"id":"253","parent":"247","text":"Empiema subdural","guid":"TjjVf20vvVI4vGCl4pqiQg","children":[]},{"id":"254","parent":"247","text":"Trombosis de la arteria carótida","guid":"2YoGomtzwDpNTWZwnjMrFg","children":[]}]}]},{"id":"255","parent":"0","text":"Tratamiento","guid":"t1UtkeC0I7aC_n0FpBy0-w","children":[{"id":"256","parent":"255","text":"Sintomático\\NAnalgesia","guid":"M0Em8wM4VkO4ZJ51BiqS1w","children":[{"id":"257","parent":"256","text":"Oral","guid":"r1lDsUtQM2KHg4PbuuYONQ","children":[{"id":"258","parent":"257","text":"Paracetamol ","guid":"iBBoPWACP-oIiBDedDoPpA","children":[{"id":"259","parent":"258","text":"15 mg/kg\\N3 veces/día","guid":"2E_CrF2j_RNvXDMHBEmTTA","children":[]}]},{"id":"260","parent":"257","text":"Ibuoprofeno ","guid":"BVAOzcOUtOm7Q6plveQScQ","children":[{"id":"261","parent":"260","text":"10 mg/kg\\N3 veces/día","guid":"TP0eURDTXP-Kj5E_LzgbAA","children":[]}]}]},{"id":"262","parent":"256","text":"Tópico","guid":"ticJ1EuwmZr7ss9weL7zeQ","children":[{"id":"263","parent":"262","text":"Benzocaina ","guid":"NqoheWJqJO03nvH_lt9GbQ","children":[]},{"id":"264","parent":"262","text":"Procaina ","guid":"7aHCA8E4tOX5ILXkI0_dlQ","children":[]},{"id":"265","parent":"262","text":"Lidocaina ","guid":"gunuOaJaVOXbR_08P-Nojw","children":[]}]},{"id":"266","parent":"256","text":"No usar descongestionantes\\Nni antihistaminicos","guid":"5OYNCCT4tStsUICv3arewA","children":[]},{"id":"267","parent":"256","text":"No usar calor-frío\\Nni otros","guid":"4eDQ7jHaMxrTs69pdufZmg","children":[]}]},{"id":"268","parent":"255","text":"Antibiótico","guid":"DYgc8m1eDJ9_j_fpDdwTXw","children":[{"id":"269","parent":"268","text":"Protocolos","guid":"","children":[{"id":"270","parent":"269","text":"ATB inmediato","guid":"wtFi5nO_5wmvWWYyfo8b6Q","children":[{"id":"271","parent":"270","text":"Siempre en <6 meses","guid":"V_51eutqdRubfXugCsfD-A","children":[]},{"id":"272","parent":"270","text":"6 meses-2 años","guid":"j5VZwLpb2SDO6_JaQgL_wg","children":[{"id":"273","parent":"272","text":"Bilateral siempre","guid":"0ALoNsABezbwuLLffGac7Q","children":[]},{"id":"274","parent":"272","text":"Unilateral se recomienda","guid":"z-bMGCqX7fz8NXinnuRBgQ","children":[]}]},{"id":"275","parent":"270","text":">2 años","guid":"UzA43ChSUZuuap116dEd1w","children":[{"id":"276","parent":"275","text":"Otalgia >48h","guid":"QyZyH8RiaVB3y_4j8OP-5w","children":[]},{"id":"277","parent":"275","text":"T>39C","guid":"mTZ6tnh9MyfLhAdiVchO5w","children":[]},{"id":"278","parent":"275","text":"Bilateral","guid":"nxb7ATPNpqF-hIsksKHmyw","children":[]},{"id":"279","parent":"275","text":"Otorrea","guid":"6fPzFR9vBIrRkOh4awHFkw","children":[]},{"id":"280","parent":"275","text":"Sin acceso a seguimiento","guid":"03P5bO_ssixZepp9DP3dEw","children":[]}]}]},{"id":"281","parent":"269","text":"ATB si síntomas no\\Nmejoran en >48-72h","guid":"MNs54Ss2AHGiu6_WTGz5dQ","children":[{"id":"282","parent":"281","text":">2 años","guid":"XVDZ612ZFETNgqVXhuz3gQ","children":[{"id":"283","parent":"282","text":"Sin comorbilidades","guid":"DNPayeysbU5AK16GBMw-6w","children":[]},{"id":"284","parent":"282","text":"Clínica leve","guid":"U-wij4d6nFCPQBiEChh42A","children":[]},{"id":"285","parent":"282","text":"Sin otorrea","guid":"pCtU9zqbLvKVJMoLHn57YA","children":[]}]}]}]},{"id":"286","parent":"268","text":"Primera línea","guid":"0rs2yiz63sAtxOfnpZlo2A","children":[{"id":"287","parent":"286","text":"Amoxicilina","guid":"L8_mpPiOsMmcSRmBAnAZrA","children":[]},{"id":"288","parent":"286","text":"Amoxi/clavulanico ","guid":"W-PcrImGYwdf4CkvxVRPXw","children":[{"id":"289","parent":"288","text":"Betalactamico 30 días anteriores","guid":"FyuKuXHRXuIsaQyyzrcX4Q","children":[]},{"id":"290","parent":"288","text":"Conjuntivitis purulenta concomitante","guid":"Dtuh-VM_pUQu_opHQ_oHcQ","children":[]},{"id":"291","parent":"288","text":"Antecedentes de OMA recurrente","guid":"2sYdBEiOtJvuF9u8lCU_8Q","children":[]}]}]},{"id":"292","parent":"268","text":"Alergia penicilina","guid":"vm7B3QZuUvTmazJOHo1d8A","children":[{"id":"293","parent":"292","text":"Retardada","guid":"x6AVC12aL-ahVFTpvRHnFA","children":[{"id":"294","parent":"293","text":"Cefalosporina 3G","guid":"","children":[]}]},{"id":"295","parent":"292","text":"Inmediata","guid":"uU3JBvHXrhPnu9aWB_PSIg","children":[{"id":"296","parent":"295","text":"Macrolidos","guid":"_SJ3221jJrWNIAi5mr5Wkw","children":[{"id":"297","parent":"296","text":"Azitromicina ","guid":"s5p6egrlYK-jkof_EsKbog","children":[]}]}]}]},{"id":"298","parent":"268","text":"Duración\\Ntratamiento","guid":"IJ2XyCVDlLVZU9NJkP8A4w","children":[{"id":"299","parent":"298","text":"5-7 días","guid":"xy65z1xAeg8_L0fcXFlKCQ","children":[]},{"id":"300","parent":"298","text":"10 días\\NSi","guid":"cU-kM5fI1u2FvwwQCsClwQ","children":[{"id":"301","parent":"300","text":"<2 años","guid":"gZ8uIoTKwtgdyaJt-bfF8A","children":[]},{"id":"302","parent":"300","text":"Perforación tímpano","guid":"fgb1NbC4KDjYsqUFTrcaxA","children":[]},{"id":"303","parent":"300","text":"Antecedentes de OMA recurrente","guid":"Ws-rukrcTwthZzbyough7w","children":[]}]}]},{"id":"304","parent":"268","text":"Seguimiento","guid":"j9dv-ZImkNbf68n5wuw8Tw","children":[{"id":"305","parent":"304","text":"Declina sintomatología <72h","guid":"mV-dRM7p_-7LQMVpxNDvcw","children":[]},{"id":"306","parent":"304","text":"Resolución síntomas 8-12 semanas","guid":"6LcQ95-wSyRNaw5Qz60TKA","children":[]}]}]},{"id":"307","parent":"255","text":"Perforación\\Ntímpano","guid":"nYC-VtxkLWJfRvxoV87jMg","children":[{"id":"308","parent":"307","text":"No utilizar agentes tópicos","guid":"SkmuKYn-1QhcZXEGebJLig","children":[]},{"id":"309","parent":"307","text":"Resolucion en  <3 meses","guid":"pv9vIUOEScsx_n9KTfPJCw","children":[{"id":"310","parent":"309","text":"Derivar a otorrino ","guid":"aEZUQNrsw8u9-rfbINJvKg","children":[]}]}]}]}]},"node_count":310,"relations":[],"cross_references":[],"specialty":"Pediatría","folder":"Entidades clínicas/Pediatría","filename":"Ped TS 01 Otitis media aguda pediatría","id":"map_2113","resolved_references":[],"title_raw":"Ped TS 01 Otitis media aguda pediatría"}