{"title":"PP3 10 Estenosis hipertrofica del piloro","guid":"","filepath":"/Users/criaah/Vault/📚 Resources/Mapas-Mentales/Entidades clínicas/Pediatría/Ped PP3 10 Estenosis hipertrofica del piloro.smmx","root":{"id":"0","parent":"-1","text":"Estenosis hipertrofica del piloro","guid":"QCSohLUlc0KyTS-qExXOuw","children":[{"id":"1","parent":"0","text":"Definición","guid":"y9Xe3VEwz6InWn7r-pHX6w","children":[{"id":"2","parent":"1","text":"Disminución progresiva\\Ndel lumen pilorico","guid":"-r6KruI4RCA1Z91zhhUg3Q","children":[]},{"id":"3","parent":"1","text":"Hipertrofia e hiperplasia\\Nde capa muscular","guid":"l__SuRrZnBD_YAV9Zt1qzA","children":[]},{"id":"4","parent":"1","text":"Impide vaciamiento gastrico","guid":"9nq4DM2MhxG1hTWMjbymuw","children":[]}]},{"id":"5","parent":"0","text":"Incidencia","guid":"MCbv0U3-BSSFvhh6EobDnA","children":[{"id":"6","parent":"5","text":"3sem - 3 mes","guid":"QMck_BY8wJoOENReCQLDIw","children":[]},{"id":"7","parent":"5","text":"1,5-4:1.000 NV","guid":"68q4UK_pfUaIoQ7TFXtiJw","children":[{"id":"8","parent":"7","text":"50%\\NPrimera gestación","guid":"","children":[]}]},{"id":"9","parent":"5","text":"H>M\\N2-7:1","guid":"7CM2lEXmyhiiHIFQmffU8w","children":[]}]},{"id":"10","parent":"0","text":"Etiopatologia\\NAlcalosis metabolica","guid":"7Z65nPE1U7Bcyu2Nuyz2Mw","children":[{"id":"11","parent":"10","text":"Vomitos","guid":"ZGFyn60Ax-_Vd5MCVhu9Lg","children":[]},{"id":"12","parent":"10","text":"Perdida HCl","guid":"2i8nBr23i_vLUY9uka3W1g","children":[]}]},{"id":"13","parent":"0","text":"Manejo","guid":"KiiTau99G_lr5gy1_WX1Uw","children":[{"id":"14","parent":"13","text":"No urgencia quirurgica","guid":"i_KFDP3EqES7sgEup8gzEg","children":[]},{"id":"15","parent":"13","text":"Estabilizar","guid":"kWhLlWg77c8MoWrPgUb6uw","children":[{"id":"16","parent":"15","text":"Metabolico","guid":"dRuwB9hkhlA6XQCm_vVMdw","children":[]},{"id":"17","parent":"15","text":"Hidroelectrlitico","guid":"43x9PIG-nc1A_96MMcaLnw","children":[]}]},{"id":"18","parent":"13","text":"Ante vomitos","guid":"","children":[{"id":"19","parent":"18","text":"Semisentado","guid":"0ZfwYVnPPbTV8oZ95kYHVw","children":[]},{"id":"20","parent":"18","text":"SNG","guid":"PF1AE0qYdUjnwJdIgCAnog","children":[]}]},{"id":"21","parent":"13","text":"Preparar pabellon","guid":"nKBPiuEsnAOjSapPf7NjiQ","children":[]}]}]},"node_count":21,"relations":[],"cross_references":[],"specialty":"Pediatría","folder":"Entidades clínicas/Pediatría","filename":"Ped PP3 10 Estenosis hipertrofica del piloro","id":"map_2039","resolved_references":[],"title_raw":"Ped PP3 10 Estenosis hipertrofica del piloro"}